<?xml version="1.0" encoding="utf-8"?>

<schemalist>

	<schema path="/priv/dis/planc/" id="priv.dis.planc" gettext-domain="test">

		<key name='tab-layout' type='i'>
			<default>0</default>
			<range min="0" max="2"/>
			<summary>Tab Layout</summary>
			<description>
				Decide on the layout tabs should be on a new window
			</description>
		</key>
		<key name='tab-autohide' type='b'>
			<default>false</default>
			<summary>Autohide Tab</summary>
			<description>
				Hide tab interface when only one tab is in a window
			</description>
		</key>
		<key name='download-domain' type='b'>
			<default>false</default>
			<summary>Download files to domain folders</summary>
			<description>
				When downloading files to default directory create a folder named after the page domain it came from and save it there
			</description>
		</key>
		<key name='planc-init' type='b'>
			<default>false</default>
			<summary>Settings Initialized</summary>
			<description>
				Has user started the program and initialized defaults
			</description>
		</key>
		<key name='planc-inhibit' type='b'>
			<default>true</default>
			<summary>Inhibit idle behaviour during audio playback</summary>
			<description>
				Do not allow a screensaver to start or the screen to blank while the current tab is playing audio
			</description>
		</key>
		<key name='webkit-cache' type='b'>
			<default>true</default>
			<summary>Memory Cache</summary>
			<description>
				Is Memory Cache enabled.
				Memory Cache (not to be confused with Disk Cache) keeps pages suspended in memory to accellerate the process of navigating back/forward between them.
				Users with low system memory and/or high disk I/O performance should consider disabling this option.
				Enabled by default for performance.
			</description>
		</key>
		<key name="webkit-encoding" type="s">
			<default l10n="messages">"utf-8"</default>
			<summary>Default Encoding</summary>
			<description>
				The type of encoding to text encoding to use when webkit has no hints from metadata
			</description>
		</key>
		<key name='webkit-hw' type='i'>
			<default>1</default>
			<range min="0" max="2"/>
			<summary>Hardware Accelleration</summary>
			<description>
				Should webkit allow hardware accelleration
			</description>
		</key>
		<key name='webkit-java' type='b'>
			<default>false</default>
			<summary>Java execution</summary>
			<description>
				Is Java allowed to run.
				Is Java (not to be confused with JavaScript) allowed to be executed by webkit.
				Disable by default for security.
			</description>
		</key>
		<key name='webkit-js' type='b'>
			<default>true</default>
			<summary>JavaScript execution</summary>
			<description>
				Is JavaScript allowed to run.
				Is JavaScript (not to be confused with Java) allowed to be executed by webkit.
				JavaScript has become the defacto scripting language in HTML5. Disabling this option may make some websites not display correctly.
				This is a master switch, disabling this feature will override all settings in the application that contradict it. If you want to disable/enable JavaScript on certian domains use configure Domain Policies within Plan C.
				Enabled by default for compatibility.
			</description>
		</key>
		<key name='webkit-mse' type='b'>
			<default>false</default>
			<summary>Media Source Extensions</summary>
			<description>
				Is Media Source Extensions enabled.
				MSE allows a websites player to deliver blobs of multimedia content though JavaScript.
				Disabled by default for stability and security.
			</description>
		</key>
		<key name='webkit-eme' type='b'>
			<default>false</default>
			<summary>Encrypted Media Extensions</summary>
			<description>
				Is Encrypted Media Extensions enabled.
				EME allows JavaScript to be used for playing encrypted media in HTML.
				Disabled by default due to controversial nature of the standard.
			</description>
		</key>
		<key name='webkit-webaudio' type='b'>
			<default>false</default>
			<summary>Web Audio API</summary>
			<description>
				Is WebAudio enabled.
				WebAudio allows webpages to generate Audio WAVE data from JavaScript.
				Disabled by default for stability.
			</description>
		</key>
		<key name='webkit-rtc' type='b'>
			<default>false</default>
			<summary>Web Real-Time Communication</summary>
			<description>
				Is WebRTC enabled or not.
				WebRTC allows websites to get multimedia input from periphrals such as a microphone or webcam.
				Disabled by default for privacy.
			</description>
		</key>
		<key name='webkit-ppt' type='b'>
			<default>false</default>
			<summary>Processes Per Tab</summary>
			<description>
				Is webkit running each tab in it's own process.
				PPT segregates each tab from the others. In the event a tab crashes or freezes, it will not effect other tabs but this comes at the cost of additional memory overhead.
				This setting will not take effect until program restart.
				Disabled by default for resource management.
			</description>
		</key>
		<key name='webkit-mcm' type='i'>
			<default>1</default>
			<range min="0" max="2"/>
			<summary>Memory Cache Model</summary>
			<description>
				How should webkit handle caching content
			</description>
		</key>
		<key name='webkit-plugins' type='b'>
			<default>false</default>
			<summary>Third Party Plugins</summary>
			<description>
				Is webkit allowed to run third party plugins.
				Plugins are small programs that are embedded into webpages to provide functionality that can't (or could not when the page was developed) be achieved though standard web technoligies.
				Disabled by default for security.
			</description>
		</key>
		<key name='webkit-dev' type='b'>
			<default>false</default>
			<summary>Webkit Developer Options</summary>
			<description>
				Enable Webkit Inspector
			</description>
		</key>
		<key name='planc-traditional' type='b'>
			<default>false</default>
			<summary>Force Traditional Menu</summary>
			<description>
				Force Plan C to use the traditional full menu even if the desktop enviroment handles a Gmenu
			</description>
		</key>
		<key name='planc-search-implicit' type='b'>
			<default>false</default>
			<summary>Allow Implicit Searching</summary>
			<description>
				Allow addressbar requests that look like a search to be handled by the default search engine
			</description>
		</key>
		<key name='planc-tabs-hover' type='b'>
			<default>false</default>
			<summary>Switch tabs on hover</summary>
			<description>
				Switch when hovering over an entry in the tabs menu
			</description>
		</key>
		<key name='planc-forward-unknown-protocol' type='b'>
			<default>false</default>
			<summary>Forward unknown protocol links to the operating system</summary>
			<description>
				Try send any uri protocol that webkit can't understand to the system automatically in the hopes that an assigned application will deal with it intelligently
			</description>
		</key>
		<key name='planc-compact-toolbar' type='b'>
			<default>false</default>
			<summary>Use a compact toolbar interface</summary>
			<description>
				Use a compact toolbar interface that intergrates most controls into the header
			</description>
		</key>
		<key name="planc-history-clean" type="i">
			<default>4</default>
			<range min="0" max="5"/>
			<summary>Automatic history cleaning</summary>
			<description>
				Decide how often to clean out the history database
			</description>
		</key>
		<key name="planc-startpage" type="s">
			<default l10n="messages">"about:blank"</default>
			<summary>Startup page</summary>
			<description>
				The page to load on browser start
			</description>
		</key>
		<key name="planc-homepage" type="s">
			<default l10n="messages">"about:blank"</default>
			<summary>Homepage</summary>
			<description>
				The page to go to when home is clicked
			</description>
		</key>
		<key name="tab-newpage" type="s">
			<default l10n="messages">"about:blank"</default>
			<summary>New Tab Page</summary>
			<description>
				The page to load in a new tab when none is specified
			</description>
		</key>
		<key name="planc-search" type="s">
			<default l10n="messages">" "</default>
			<summary>Default Search</summary>
			<description>
				The search engine to use when no key is specified
			</description>
		</key>
	</schema>

</schemalist>
